pythonhelpers/__init__.py
pythonhelpers/helper_functions.py
pythonhelpers-0.0.1rc0.dist-info/LICENSE.txt
pythonhelpers-0.0.1rc0.dist-info/METADATA
pythonhelpers-0.0.1rc0.dist-info/WHEEL
pythonhelpers-0.0.1rc0.dist-info/top_level.txt
pythonhelpers-0.0.1rc0.dist-info/RECORD
